{
  "id": "module.search",
  "name": "search",
  "title": "Search",
  "version": "1.3.0",
  "kind": "business_module",
  "requires": [
    "authentication"
  ],
  "optional": [
    "products",
    "booking",
    "customers"
  ],
  "conflicts": [],
  "supports": [
    "saas",
    "crm",
    "marketplace",
    "booking",
    "ecommerce"
  ],
  "surfaces": {
    "schema": "schema/",
    "api": "api/",
    "frontend": "frontend/",
    "backend": "backend/",
    "tests": "tests/",
    "docs": "docs/"
  },
  "artifacts": {
    "entities": [
      "search_index"
    ],
    "endpoints": [
      "GET /search"
    ],
    "ui": [
      "SearchBox"
    ],
    "permissions": [
      "search.use"
    ]
  }
}
